mettle/__init__.py
mettle/cli.py
mettle/db.py
mettle/dispatcher.py
mettle/lock.py
mettle/logcollector.py
mettle/models.py
mettle/notify.py
mettle/publisher.py
mettle/settings.py
mettle/timer.py
mettle/migrations/__init__.py
mettle/migrations/0001-create-migrations-table/forward.sql
mettle/migrations/0002-initial-tables/forward.sql
mettle/migrations/0003-add-change-triggers/forward.sql
mettle/migrations/0004-misc-columns/forward.sql
mettle/migrations/0005-notify-triggers/forward.sql
mettle/migrations/0006-services.pipeline_names/forward.sql
mettle/migrations/0007-pipelines_runs_nacks/forward.sql
mettle/migrations/0008-target_parameters/forward.sql
mettle/migrations/0009-fix-change-triggers/forward.sql
mettle/migrations/0010-notifications/forward.sql
mettle/migrations/0011-pipeline-run-chained-from/forward.sql
mettle/migrations/0012-fix-pipeline-run-chained-from/forward.sql
mettle/migrations/0013-add-checkins-table/forward.sql
mettle/static/.bowerrc
mettle/static/bower.json
mettle/static/message_flow.html
mettle/static/css/mettle.css
mettle/static/font/roboto/Google Android License.txt
mettle/static/font/roboto/Roboto-Black-webfont.woff
mettle/static/font/roboto/Roboto-BlackItalic-webfont.woff
mettle/static/font/roboto/Roboto-Bold-webfont.woff
mettle/static/font/roboto/Roboto-BoldCondensed-webfont.woff
mettle/static/font/roboto/Roboto-BoldCondensedItalic-webfont.woff
mettle/static/font/roboto/Roboto-BoldItalic-webfont.woff
mettle/static/font/roboto/Roboto-Condensed-webfont.woff
mettle/static/font/roboto/Roboto-CondensedItalic-webfont.woff
mettle/static/font/roboto/Roboto-Italic-webfont.woff
mettle/static/font/roboto/Roboto-Light-webfont.woff
mettle/static/font/roboto/Roboto-LightItalic-webfont.woff
mettle/static/font/roboto/Roboto-Medium-webfont.woff
mettle/static/font/roboto/Roboto-MediumItalic-webfont.woff
mettle/static/font/roboto/Roboto-Regular-webfont.woff
mettle/static/font/roboto/Roboto-Thin-webfont.woff
mettle-0.7.14.dist-info/DESCRIPTION.rst
mettle-0.7.14.dist-info/METADATA
mettle-0.7.14.dist-info/RECORD
mettle-0.7.14.dist-info/WHEEL
mettle-0.7.14.dist-info/entry_points.txt
mettle-0.7.14.dist-info/metadata.json
mettle-0.7.14.dist-info/namespace_packages.txt
mettle-0.7.14.dist-info/top_level.txt
