Metadata-Version: 2.0
Name: mettle
Version: 0.7.14
Summary: A micro service framework for data pipelines, providingscheduling, retrying, and error reporting.
Home-page: https://github.com/yougov/mettle
Author: YouGov, Plc.
Author-email: opensource@yougov.com
License: UNKNOWN
Platform: UNKNOWN
Classifier: Development Status :: 5 - Production/Stable
Classifier: Intended Audience :: Developers
Classifier: License :: OSI Approved :: MIT License
Classifier: Programming Language :: Python :: 2.7
Requires-Python: >=2.7,<3.0
Provides-Extra: testing
Provides-Extra: docs
Requires-Dist: Beaker (==1.6.4)
Requires-Dist: croniter (==0.3.5)
Requires-Dist: functools32 (==3.2.3-1)
Requires-Dist: gevent (==1.1.2)
Requires-Dist: gunicorn (==19.1.1)
Requires-Dist: gwebsocket (==0.9.8)
Requires-Dist: iso8601 (>=0.1.10)
Requires-Dist: pgpubsub (>=0.0.4)
Requires-Dist: psycogreen (==1.0)
Requires-Dist: psycopg2 (==2.7.4)
Requires-Dist: PyYAML (==3.11)
Requires-Dist: spa (==0.0.7)
Requires-Dist: sqlalchemy (==0.9.8)
Requires-Dist: Werkzeug (==0.10.1)
Requires-Dist: mettle-protocol (>=1.0.1)
Requires-Dist: pika (<0.10.0,>=0.9.14)
Requires-Dist: utc
Provides-Extra: docs
Requires-Dist: sphinx; extra == 'docs'
Requires-Dist: jaraco.packaging (>=3.2); extra == 'docs'
Requires-Dist: rst.linker (>=1.9); extra == 'docs'
Provides-Extra: testing
Requires-Dist: pytest (>=2.8); extra == 'testing'
Requires-Dist: pytest-sugar; extra == 'testing'
Requires-Dist: collective.checkdocs; extra == 'testing'
